fieldenum/__init__.py
fieldenum/_fieldenum.py
fieldenum/_utils.py
fieldenum/enums.py
fieldenum/exceptions.py
fieldenum-0.2.0.dist-info/LICENSE
fieldenum-0.2.0.dist-info/METADATA
fieldenum-0.2.0.dist-info/WHEEL
fieldenum-0.2.0.dist-info/RECORD
