Metadata-Version: 2.1
Name: fieldenum
Version: 0.2.0
Summary: Rust-like fielded Enums in Python
License: MIT
Keywords: enum,dataclass,rust,functional
Author: ilotoki0804
Author-email: ilotoki0804@gmail.com
Requires-Python: >=3.10,<4.0
Classifier: Intended Audience :: Developers
Classifier: License :: OSI Approved :: MIT License
Classifier: Natural Language :: Korean
Classifier: Operating System :: OS Independent
Classifier: Programming Language :: Python :: 3
Classifier: Programming Language :: Python :: 3.10
Classifier: Programming Language :: Python :: 3.11
Classifier: Programming Language :: Python :: 3.12
Classifier: Programming Language :: Rust
Classifier: Typing :: Typed
Project-URL: Repository, https://github.com/ilotoki0804/fieldenum
